spatial_dynamics/n_simplex_neighborhoods.py
spatial_dynamics/pwlo-es-pt.py
spatial_dynamics-0.1.0.dist-info/METADATA
spatial_dynamics-0.1.0.dist-info/WHEEL
spatial_dynamics-0.1.0.dist-info/entry_points.txt
spatial_dynamics-0.1.0.dist-info/top_level.txt
spatial_dynamics-0.1.0.dist-info/RECORD
