Metadata-Version: 2.4
Name: spatial-dynamics
Version: 0.1.0
Summary: A package for spatial dynamics analysis of cell neighborhoods
Author-email: Eduardo Esteva <Eduardo.Esteva@nyulangone.org>
License: MIT
Project-URL: Homepage, https://github.com/e-esteva/spatial-dynamics
Project-URL: Bug Tracker, https://github.com/e-esteva/spatial-dynamics/issues
Project-URL: Documentation, https://spatial-dynamics.readthedocs.io/
Keywords: spatial analysis,bioinformatics,cell neighborhoods,spatial statistics
Classifier: Development Status :: 3 - Alpha
Classifier: Intended Audience :: Science/Research
Classifier: Topic :: Scientific/Engineering :: Bio-Informatics
Classifier: License :: OSI Approved :: MIT License
Classifier: Programming Language :: Python :: 3
Classifier: Programming Language :: Python :: 3.8
Classifier: Programming Language :: Python :: 3.9
Classifier: Programming Language :: Python :: 3.10
Classifier: Programming Language :: Python :: 3.11
Requires-Python: >=3.8
Requires-Dist: numpy>=1.21.0
Requires-Dist: pandas>=1.3.0
Requires-Dist: scipy>=1.7.0
Provides-Extra: dev
Requires-Dist: pytest>=6.0; extra == "dev"
Requires-Dist: pytest-cov; extra == "dev"
Requires-Dist: black; extra == "dev"
Requires-Dist: flake8; extra == "dev"
Requires-Dist: mypy; extra == "dev"
Requires-Dist: pre-commit; extra == "dev"
Provides-Extra: docs
Requires-Dist: sphinx; extra == "docs"
Requires-Dist: sphinx-rtd-theme; extra == "docs"
